streamlit_image_select_jun/__init__.py
streamlit_image_select_jun/frontend/.env
streamlit_image_select_jun/frontend/.prettierrc
streamlit_image_select_jun/frontend/package-lock.json
streamlit_image_select_jun/frontend/package.json
streamlit_image_select_jun/frontend/public/index.html
streamlit_image_select_jun/frontend/public/styles.css
streamlit_image_select_jun/frontend/src/index.tsx
streamlit_image_select_jun/frontend/src/react-app-env.d.ts
streamlit_image_select_jun/frontend/tsconfig.json
streamlit_image_select_jun-0.0.1.dist-info/LICENSE
streamlit_image_select_jun-0.0.1.dist-info/WHEEL
streamlit_image_select_jun-0.0.1.dist-info/METADATA
streamlit_image_select_jun-0.0.1.dist-info/RECORD
